setup.py
bin/areastats
bin/climstats
climstats/__init__.py
climstats/dataset.py
climstats/dataset_old.py
climstats/functions.py
climstats/gridfunctions.py
climstats/grouping.py
climstats/plotting.py
climstats/postgres.py
climstats/slicing.py
climstats.egg-info/PKG-INFO
climstats.egg-info/SOURCES.txt
climstats.egg-info/dependency_links.txt
climstats.egg-info/not-zip-safe
climstats.egg-info/pbr.json
climstats.egg-info/requires.txt
climstats.egg-info/top_level.txt