Metadata-Version: 1.0
Name: climstats
Version: 0.1.1
Summary: Multi-dimensional environmental data manipulation and statitics
Home-page: https://github.com/csag-uct/climstats
Author: Jackaranda
Author-email: cjack@csag.uct.ac.za
License: Apache
Platform: UNKNOWN
